[
  {
    "esporte": "Tênis",
    "competicao": "Monte Carlo",
    "titulo": "Joao Fonseca vs Arthur Rinderknech",
    "data": "08/04",
    "hora": "07:35",
    "data_ordem": "2026-04-08T07:35:00-03:00",
    "dias_ate": -2,
    "status": "resultado",
    "resultado": "2 x 1",
    "transmissao": "ESPN / Disney+",
    "prioridade": 1,
    "origem": "Monte Carlo",
    "tipo": "evento",
    "destaque": true,
    "fonte": "tennisapi1",
    "rodada": "Round of 32",
    "mandante": null,
    "visitante": null,
    "estadio": null,
    "cidade": null,
    "uf": null
  },
  {
    "esporte": "Tênis",
    "competicao": "Monte Carlo",
    "titulo": "Matteo Berrettini vs Joao Fonseca",
    "data": "09/04",
    "hora": "06:00",
    "data_ordem": "2026-04-09T06:00:00-03:00",
    "dias_ate": -1,
    "status": "resultado",
    "resultado": "0 x 2",
    "transmissao": "ESPN / Disney+",
    "prioridade": 1,
    "origem": "Monte Carlo",
    "tipo": "evento",
    "destaque": true,
    "fonte": "tennisapi1",
    "rodada": "Round of 16",
    "mandante": null,
    "visitante": null,
    "estadio": null,
    "cidade": null,
    "uf": null
  },
  {
    "esporte": "Tênis",
    "competicao": "Monte Carlo",
    "titulo": "Joao Fonseca vs Alexander Zverev",
    "data": "10/04",
    "hora": "06:00",
    "data_ordem": "2026-04-10T06:00:00-03:00",
    "dias_ate": 0,
    "status": "resultado",
    "resultado": null,
    "transmissao": "ESPN / Disney+",
    "prioridade": 1,
    "origem": "Monte Carlo",
    "tipo": "evento",
    "destaque": true,
    "fonte": "tennisapi1",
    "rodada": "Quarterfinals",
    "mandante": null,
    "visitante": null,
    "estadio": null,
    "cidade": null,
    "uf": null
  },
  {
    "esporte": "Futebol",
    "competicao": "Libertadores",
    "titulo": "CS Independiente Rivadavia vs Club Bolívar",
    "data": "07/04",
    "hora": "19:00",
    "data_ordem": "2026-04-07T19:00:00-03:00",
    "dias_ate": -3,
    "status": "resultado",
    "resultado": "1 x 0",
    "transmissao": "Globo / ESPN / Disney+ / ge tv",
    "prioridade": 3,
    "origem": "Libertadores",
    "tipo": "evento",
    "destaque": false,
    "fonte": "football-data.org / Libertadores",
    "rodada": 1,
    "mandante": "CS Independiente Rivadavia",
    "visitante": "Club Bolívar",
    "estadio": null,
    "cidade": null,
    "uf": null
  },
  {
    "esporte": "Futebol",
    "competicao": "Libertadores",
    "titulo": "Deportivo La Guaira FC vs Fluminense FC",
    "data": "07/04",
    "hora": "19:00",
    "data_ordem": "2026-04-07T19:00:00-03:00",
    "dias_ate": -3,
    "status": "resultado",
    "resultado": "0 x 0",
    "transmissao": "Globo / ESPN / Disney+ / ge tv",
    "prioridade": 3,
    "origem": "Libertadores",
    "tipo": "evento",
    "destaque": false,
    "fonte": "football-data.org / Libertadores",
    "rodada": 1,
    "mandante": "Deportivo La Guaira FC",
    "visitante": "Fluminense FC",
    "estadio": null,
    "cidade": null,
    "uf": null
  },
  {
    "esporte": "Futebol",
    "competicao": "Libertadores",
    "titulo": "Barcelona SC vs Cruzeiro EC",
    "data": "07/04",
    "hora": "21:00",
    "data_ordem": "2026-04-07T21:00:00-03:00",
    "dias_ate": -3,
    "status": "resultado",
    "resultado": "0 x 1",
    "transmissao": "Globo / ESPN / Disney+ / ge tv",
    "prioridade": 3,
    "origem": "Libertadores",
    "tipo": "evento",
    "destaque": false,
    "fonte": "football-data.org / Libertadores",
    "rodada": 1,
    "mandante": "Barcelona SC",
    "visitante": "Cruzeiro EC",
    "estadio": null,
    "cidade": null,
    "uf": null
  },
  {
    "esporte": "Futebol",
    "competicao": "Libertadores",
    "titulo": "Club Always Ready vs LDU de Quito",
    "data": "07/04",
    "hora": "21:00",
    "data_ordem": "2026-04-07T21:00:00-03:00",
    "dias_ate": -3,
    "status": "resultado",
    "resultado": "0 x 1",
    "transmissao": "Globo / ESPN / Disney+ / ge tv",
    "prioridade": 3,
    "origem": "Libertadores",
    "tipo": "evento",
    "destaque": false,
    "fonte": "football-data.org / Libertadores",
    "rodada": 1,
    "mandante": "Club Always Ready",
    "visitante": "LDU de Quito",
    "estadio": null,
    "cidade": null,
    "uf": null
  },
  {
    "esporte": "Futebol",
    "competicao": "Libertadores",
    "titulo": "CD Universidad Católica vs CA Boca Juniors",
    "data": "07/04",
    "hora": "21:30",
    "data_ordem": "2026-04-07T21:30:00-03:00",
    "dias_ate": -3,
    "status": "resultado",
    "resultado": "1 x 2",
    "transmissao": "Globo / ESPN / Disney+ / ge tv",
    "prioridade": 3,
    "origem": "Libertadores",
    "tipo": "evento",
    "destaque": false,
    "fonte": "football-data.org / Libertadores",
    "rodada": 1,
    "mandante": "CD Universidad Católica",
    "visitante": "CA Boca Juniors",
    "estadio": null,
    "cidade": null,
    "uf": null
  },
  {
    "esporte": "Futebol",
    "competicao": "Libertadores",
    "titulo": "CD Tolima vs Club Universitario de Deportes",
    "data": "07/04",
    "hora": "23:00",
    "data_ordem": "2026-04-07T23:00:00-03:00",
    "dias_ate": -3,
    "status": "resultado",
    "resultado": "0 x 0",
    "transmissao": "Globo / ESPN / Disney+ / ge tv",
    "prioridade": 3,
    "origem": "Libertadores",
    "tipo": "evento",
    "destaque": false,
    "fonte": "football-data.org / Libertadores",
    "rodada": 1,
    "mandante": "CD Tolima",
    "visitante": "Club Universitario de Deportes",
    "estadio": null,
    "cidade": null,
    "uf": null
  },
  {
    "esporte": "Tênis",
    "competicao": "Monte Carlo",
    "titulo": "Cristian Garin vs Alexander Zverev",
    "data": "08/04",
    "hora": "07:10",
    "data_ordem": "2026-04-08T07:10:00-03:00",
    "dias_ate": -2,
    "status": "resultado",
    "resultado": "1 x 2",
    "transmissao": "ESPN / Disney+",
    "prioridade": 3,
    "origem": "Monte Carlo",
    "tipo": "evento",
    "destaque": false,
    "fonte": "tennisapi1",
    "rodada": "Round of 32",
    "mandante": null,
    "visitante": null,
    "estadio": null,
    "cidade": null,
    "uf": null
  },
  {
    "esporte": "Tênis",
    "competicao": "Monte Carlo",
    "titulo": "Felix Auger-Aliassime vs Marin Čilić",
    "data": "08/04",
    "hora": "10:35",
    "data_ordem": "2026-04-08T10:35:00-03:00",
    "dias_ate": -2,
    "status": "resultado",
    "resultado": "2 x 0",
    "transmissao": "ESPN / Disney+",
    "prioridade": 3,
    "origem": "Monte Carlo",
    "tipo": "evento",
    "destaque": false,
    "fonte": "tennisapi1",
    "rodada": "Round of 32",
    "mandante": null,
    "visitante": null,
    "estadio": null,
    "cidade": null,
    "uf": null
  },
  {
    "esporte": "Tênis",
    "competicao": "Monte Carlo",
    "titulo": "Lorenzo Musetti vs Valentin Vacherot",
    "data": "08/04",
    "hora": "12:55",
    "data_ordem": "2026-04-08T12:55:00-03:00",
    "dias_ate": -2,
    "status": "resultado",
    "resultado": "0 x 2",
    "transmissao": "ESPN / Disney+",
    "prioridade": 3,
    "origem": "Monte Carlo",
    "tipo": "evento",
    "destaque": false,
    "fonte": "tennisapi1",
    "rodada": "Round of 32",
    "mandante": null,
    "visitante": null,
    "estadio": null,
    "cidade": null,
    "uf": null
  },
  {
    "esporte": "Futebol",
    "competicao": "Libertadores",
    "titulo": "CD Coquimbo Unido vs Club Nacional de Football",
    "data": "08/04",
    "hora": "19:00",
    "data_ordem": "2026-04-08T19:00:00-03:00",
    "dias_ate": -2,
    "status": "resultado",
    "resultado": "1 x 1",
    "transmissao": "Globo / ESPN / Disney+ / ge tv",
    "prioridade": 3,
    "origem": "Libertadores",
    "tipo": "evento",
    "destaque": false,
    "fonte": "football-data.org / Libertadores",
    "rodada": 1,
    "mandante": "CD Coquimbo Unido",
    "visitante": "Club Nacional de Football",
    "estadio": null,
    "cidade": null,
    "uf": null
  },
  {
    "esporte": "Futebol",
    "competicao": "Libertadores",
    "titulo": "Mirassol FC vs CA Lanús",
    "data": "08/04",
    "hora": "19:00",
    "data_ordem": "2026-04-08T19:00:00-03:00",
    "dias_ate": -2,
    "status": "resultado",
    "resultado": "1 x 0",
    "transmissao": "Globo / ESPN / Disney+ / ge tv",
    "prioridade": 3,
    "origem": "Libertadores",
    "tipo": "evento",
    "destaque": false,
    "fonte": "football-data.org / Libertadores",
    "rodada": 1,
    "mandante": "Mirassol FC",
    "visitante": "CA Lanús",
    "estadio": null,
    "cidade": null,
    "uf": null
  },
  {
    "esporte": "Futebol",
    "competicao": "Libertadores",
    "titulo": "CD Independiente Medellín vs Estudiantes de La Plata",
    "data": "08/04",
    "hora": "21:00",
    "data_ordem": "2026-04-08T21:00:00-03:00",
    "dias_ate": -2,
    "status": "resultado",
    "resultado": "1 x 1",
    "transmissao": "Globo / ESPN / Disney+ / ge tv",
    "prioridade": 3,
    "origem": "Libertadores",
    "tipo": "evento",
    "destaque": false,
    "fonte": "football-data.org / Libertadores",
    "rodada": 1,
    "mandante": "CD Independiente Medellín",
    "visitante": "Estudiantes de La Plata",
    "estadio": null,
    "cidade": null,
    "uf": null
  },
  {
    "esporte": "Futebol",
    "competicao": "Libertadores",
    "titulo": "Cusco FC vs CR Flamengo",
    "data": "08/04",
    "hora": "21:30",
    "data_ordem": "2026-04-08T21:30:00-03:00",
    "dias_ate": -2,
    "status": "resultado",
    "resultado": "0 x 2",
    "transmissao": "Globo / ESPN / Disney+ / ge tv",
    "prioridade": 3,
    "origem": "Libertadores",
    "tipo": "evento",
    "destaque": false,
    "fonte": "football-data.org / Libertadores",
    "rodada": 1,
    "mandante": "Cusco FC",
    "visitante": "CR Flamengo",
    "estadio": null,
    "cidade": null,
    "uf": null
  },
  {
    "esporte": "Futebol",
    "competicao": "Libertadores",
    "titulo": "CDP Junior FC vs SE Palmeiras",
    "data": "08/04",
    "hora": "21:30",
    "data_ordem": "2026-04-08T21:30:00-03:00",
    "dias_ate": -2,
    "status": "resultado",
    "resultado": "1 x 1",
    "transmissao": "Globo / ESPN / Disney+ / ge tv",
    "prioridade": 3,
    "origem": "Libertadores",
    "tipo": "evento",
    "destaque": false,
    "fonte": "football-data.org / Libertadores",
    "rodada": 1,
    "mandante": "CDP Junior FC",
    "visitante": "SE Palmeiras",
    "estadio": null,
    "cidade": null,
    "uf": null
  },
  {
    "esporte": "Futebol",
    "competicao": "Libertadores",
    "titulo": "CS Cristal vs Club Cerro Porteño",
    "data": "08/04",
    "hora": "23:00",
    "data_ordem": "2026-04-08T23:00:00-03:00",
    "dias_ate": -2,
    "status": "resultado",
    "resultado": "1 x 0",
    "transmissao": "Globo / ESPN / Disney+ / ge tv",
    "prioridade": 3,
    "origem": "Libertadores",
    "tipo": "evento",
    "destaque": false,
    "fonte": "football-data.org / Libertadores",
    "rodada": 1,
    "mandante": "CS Cristal",
    "visitante": "Club Cerro Porteño",
    "estadio": null,
    "cidade": null,
    "uf": null
  },
  {
    "esporte": "Tênis",
    "competicao": "Monte Carlo",
    "titulo": "Zizou Bergs vs Alexander Zverev",
    "data": "09/04",
    "hora": "06:00",
    "data_ordem": "2026-04-09T06:00:00-03:00",
    "dias_ate": -1,
    "status": "resultado",
    "resultado": "0 x 2",
    "transmissao": "ESPN / Disney+",
    "prioridade": 3,
    "origem": "Monte Carlo",
    "tipo": "evento",
    "destaque": false,
    "fonte": "tennisapi1",
    "rodada": "Round of 16",
    "mandante": null,
    "visitante": null,
    "estadio": null,
    "cidade": null,
    "uf": null
  },
  {
    "esporte": "Tênis",
    "competicao": "Monte Carlo",
    "titulo": "Felix Auger-Aliassime vs Casper Ruud",
    "data": "09/04",
    "hora": "07:30",
    "data_ordem": "2026-04-09T07:30:00-03:00",
    "dias_ate": -1,
    "status": "resultado",
    "resultado": "1 x 0",
    "transmissao": "ESPN / Disney+",
    "prioridade": 3,
    "origem": "Monte Carlo",
    "tipo": "evento",
    "destaque": false,
    "fonte": "tennisapi1",
    "rodada": "Round of 16",
    "mandante": null,
    "visitante": null,
    "estadio": null,
    "cidade": null,
    "uf": null
  },
  {
    "esporte": "Tênis",
    "competicao": "Monte Carlo",
    "titulo": "Tomaš Machač vs Jannik Sinner",
    "data": "09/04",
    "hora": "08:10",
    "data_ordem": "2026-04-09T08:10:00-03:00",
    "dias_ate": -1,
    "status": "resultado",
    "resultado": "1 x 2",
    "transmissao": "ESPN / Disney+",
    "prioridade": 3,
    "origem": "Monte Carlo",
    "tipo": "evento",
    "destaque": false,
    "fonte": "tennisapi1",
    "rodada": "Round of 16",
    "mandante": null,
    "visitante": null,
    "estadio": null,
    "cidade": null,
    "uf": null
  },
  {
    "esporte": "Tênis",
    "competicao": "Monte Carlo",
    "titulo": "Carlos Alcaraz vs Tomas Martin Etcheverry",
    "data": "09/04",
    "hora": "10:30",
    "data_ordem": "2026-04-09T10:30:00-03:00",
    "dias_ate": -1,
    "status": "resultado",
    "resultado": "2 x 1",
    "transmissao": "ESPN / Disney+",
    "prioridade": 3,
    "origem": "Monte Carlo",
    "tipo": "evento",
    "destaque": false,
    "fonte": "tennisapi1",
    "rodada": "Round of 16",
    "mandante": null,
    "visitante": null,
    "estadio": null,
    "cidade": null,
    "uf": null
  },
  {
    "esporte": "Tênis",
    "competicao": "Monte Carlo",
    "titulo": "Alexander Blockx vs Alex de Minaur",
    "data": "09/04",
    "hora": "11:20",
    "data_ordem": "2026-04-09T11:20:00-03:00",
    "dias_ate": -1,
    "status": "resultado",
    "resultado": "0 x 2",
    "transmissao": "ESPN / Disney+",
    "prioridade": 3,
    "origem": "Monte Carlo",
    "tipo": "evento",
    "destaque": false,
    "fonte": "tennisapi1",
    "rodada": "Round of 16",
    "mandante": null,
    "visitante": null,
    "estadio": null,
    "cidade": null,
    "uf": null
  },
  {
    "esporte": "Futebol",
    "competicao": "Libertadores",
    "titulo": "Universidad Central de Venezuela FC vs Club Libertad Asuncion",
    "data": "09/04",
    "hora": "19:00",
    "data_ordem": "2026-04-09T19:00:00-03:00",
    "dias_ate": -1,
    "status": "resultado",
    "resultado": "3 x 1",
    "transmissao": "Globo / ESPN / Disney+ / ge tv",
    "prioridade": 3,
    "origem": "Libertadores",
    "tipo": "evento",
    "destaque": false,
    "fonte": "football-data.org / Libertadores",
    "rodada": 1,
    "mandante": "Universidad Central de Venezuela FC",
    "visitante": "Club Libertad Asuncion",
    "estadio": null,
    "cidade": null,
    "uf": null
  },
  {
    "esporte": "Futebol",
    "competicao": "Libertadores",
    "titulo": "CA Rosario Central vs CAR Independiente del Valle",
    "data": "09/04",
    "hora": "19:00",
    "data_ordem": "2026-04-09T19:00:00-03:00",
    "dias_ate": -1,
    "status": "resultado",
    "resultado": "0 x 0",
    "transmissao": "Globo / ESPN / Disney+ / ge tv",
    "prioridade": 3,
    "origem": "Libertadores",
    "tipo": "evento",
    "destaque": false,
    "fonte": "football-data.org / Libertadores",
    "rodada": 1,
    "mandante": "CA Rosario Central",
    "visitante": "CAR Independiente del Valle",
    "estadio": null,
    "cidade": null,
    "uf": null
  },
  {
    "esporte": "Futebol",
    "competicao": "Libertadores",
    "titulo": "CA Platense vs SC Corinthians Paulista",
    "data": "09/04",
    "hora": "21:00",
    "data_ordem": "2026-04-09T21:00:00-03:00",
    "dias_ate": -1,
    "status": "resultado",
    "resultado": null,
    "transmissao": "Globo / ESPN / Disney+ / ge tv",
    "prioridade": 3,
    "origem": "Libertadores",
    "tipo": "evento",
    "destaque": false,
    "fonte": "football-data.org / Libertadores",
    "rodada": 1,
    "mandante": "CA Platense",
    "visitante": "SC Corinthians Paulista",
    "estadio": null,
    "cidade": null,
    "uf": null
  },
  {
    "esporte": "Futebol",
    "competicao": "Libertadores",
    "titulo": "Independiente Santa Fe vs CA Peñarol",
    "data": "09/04",
    "hora": "23:00",
    "data_ordem": "2026-04-09T23:00:00-03:00",
    "dias_ate": -1,
    "status": "resultado",
    "resultado": null,
    "transmissao": "Globo / ESPN / Disney+ / ge tv",
    "prioridade": 3,
    "origem": "Libertadores",
    "tipo": "evento",
    "destaque": false,
    "fonte": "football-data.org / Libertadores",
    "rodada": 1,
    "mandante": "Independiente Santa Fe",
    "visitante": "CA Peñarol",
    "estadio": null,
    "cidade": null,
    "uf": null
  },
  {
    "esporte": "Tênis",
    "competicao": "Monte Carlo",
    "titulo": "Felix Auger-Aliassime vs Jannik Sinner",
    "data": "10/04",
    "hora": "07:10",
    "data_ordem": "2026-04-10T07:10:00-03:00",
    "dias_ate": 0,
    "status": "resultado",
    "resultado": null,
    "transmissao": "ESPN / Disney+",
    "prioridade": 3,
    "origem": "Monte Carlo",
    "tipo": "evento",
    "destaque": false,
    "fonte": "tennisapi1",
    "rodada": "Quarterfinals",
    "mandante": null,
    "visitante": null,
    "estadio": null,
    "cidade": null,
    "uf": null
  },
  {
    "esporte": "Tênis",
    "competicao": "Billie Jean King Cup",
    "titulo": "Jasmine Paolini vs Himeno Sakatsume",
    "data": "10/04",
    "hora": "08:10",
    "data_ordem": "2026-04-10T08:10:00-03:00",
    "dias_ate": 0,
    "status": "resultado",
    "resultado": null,
    "transmissao": "ESPN / Disney+",
    "prioridade": 3,
    "origem": "Billie Jean King Cup",
    "tipo": "evento",
    "destaque": false,
    "fonte": "tennisapi1",
    "rodada": null,
    "mandante": null,
    "visitante": null,
    "estadio": null,
    "cidade": null,
    "uf": null
  },
  {
    "esporte": "Tênis",
    "competicao": "Monte Carlo",
    "titulo": "Carlos Alcaraz vs Alexander Bublik",
    "data": "10/04",
    "hora": "08:20",
    "data_ordem": "2026-04-10T08:20:00-03:00",
    "dias_ate": 0,
    "status": "resultado",
    "resultado": null,
    "transmissao": "ESPN / Disney+",
    "prioridade": 3,
    "origem": "Monte Carlo",
    "tipo": "evento",
    "destaque": false,
    "fonte": "tennisapi1",
    "rodada": "Quarterfinals",
    "mandante": null,
    "visitante": null,
    "estadio": null,
    "cidade": null,
    "uf": null
  },
  {
    "esporte": "Tênis",
    "competicao": "Monte Carlo",
    "titulo": "Valentin Vacherot vs Alex de Minaur",
    "data": "10/04",
    "hora": "09:30",
    "data_ordem": "2026-04-10T09:30:00-03:00",
    "dias_ate": 0,
    "status": "resultado",
    "resultado": null,
    "transmissao": "ESPN / Disney+",
    "prioridade": 3,
    "origem": "Monte Carlo",
    "tipo": "evento",
    "destaque": false,
    "fonte": "tennisapi1",
    "rodada": "Quarterfinals",
    "mandante": null,
    "visitante": null,
    "estadio": null,
    "cidade": null,
    "uf": null
  }
]